ash_model/__init__.py
ash_model/classes/__init__.py
ash_model/classes/node_profile.py
ash_model/classes/undirected.py
ash_model/measures/__init__.py
ash_model/measures/attribute_analysis.py
ash_model/measures/clustering.py
ash_model/measures/hyper_conformity.py
ash_model/measures/s_centralities.py
ash_model/models/__init__.py
ash_model/models/random.py
ash_model/paths/__init__.py
ash_model/paths/time_respecting_walks.py
ash_model/paths/walks.py
ash_model/readwrite/__init__.py
ash_model/readwrite/io.py
ash_model/utils/__init__.py
ash_model/utils/undirected_graph_transformations.py
ash_model/utils/undirected_matrices.py
ash_model/viz/__init__.py
ash_model/viz/static.py
ash_model/viz/temporal.py
ash_model-0.1.0.dist-info/LICENSE
ash_model-0.1.0.dist-info/METADATA
ash_model-0.1.0.dist-info/WHEEL
ash_model-0.1.0.dist-info/top_level.txt
ash_model-0.1.0.dist-info/RECORD
