Metadata-Version: 2.1
Name: ash-model
Version: 0.1.0
Summary: Attributed Stream Hypergraph library
Home-page: https://github.com/GiulioRossetti/ASH
Author: Giulio Rossetti
Author-email: giulio.rossetti@gmail.com
License: BSD-Clause-2
Keywords: dynamic-networks
Classifier: Development Status :: 4 - Beta 
Classifier: Intended Audience :: Developers
Classifier: Topic :: Software Development :: Build Tools
Classifier: License :: OSI Approved :: GNU General Public License v3 or later (GPLv3+)
Classifier: Operating System :: OS Independent
Classifier: Programming Language :: Python
Classifier: Programming Language :: Python :: 3
License-File: LICENSE
Requires-Dist: halp
Requires-Dist: numpy
Requires-Dist: scipy
Requires-Dist: networkx
Requires-Dist: matplotlib
Requires-Dist: seaborn
Requires-Dist: pandas
Requires-Dist: tqdm
